puanchen/__init__.py
puanchen-1.1.2.dist-info/METADATA
puanchen-1.1.2.dist-info/WHEEL
puanchen-1.1.2.dist-info/top_level.txt
puanchen-1.1.2.dist-info/RECORD
