Metadata-Version: 2.1
Name: puanchen
Version: 1.1.2
Summary: a Python implementation of message queue based on pika
Home-page: https://github.com/perfeelab/puanchen
Author: ClaireHuang
Author-email: clairehf@163.com
License: UNKNOWN
Platform: UNKNOWN
Classifier: Programming Language :: Python :: 2
Classifier: Programming Language :: Python :: 3
Classifier: License :: OSI Approved :: MIT License
Classifier: Operating System :: OS Independent
Requires-Dist: pika (>=1.0.1)
